nemo_aligner/__init__.py
nemo_aligner/package_info.py
nemo_aligner/algorithms/__init__.py
nemo_aligner/algorithms/critic_server_trainer.py
nemo_aligner/algorithms/dpo.py
nemo_aligner/algorithms/kto.py
nemo_aligner/algorithms/ppo.py
nemo_aligner/algorithms/reinforce.py
nemo_aligner/algorithms/reward_server.py
nemo_aligner/algorithms/rs.py
nemo_aligner/algorithms/spin.py
nemo_aligner/algorithms/supervised.py
nemo_aligner/data/__init__.py
nemo_aligner/data/nlp/__init__.py
nemo_aligner/data/nlp/builders.py
nemo_aligner/data/nlp/datasets.py
nemo_aligner/data/nlp/tests/__init__.py
nemo_aligner/data/nlp/tests/cai_utils_test.py
nemo_aligner/data/nlp/tests/datasets_test.py
nemo_aligner/experimental/__init__.py
nemo_aligner/metrics/__init__.py
nemo_aligner/metrics/common.py
nemo_aligner/models/__init__.py
nemo_aligner/models/alignable_interface.py
nemo_aligner/models/nlp/__init__.py
nemo_aligner/models/nlp/gpt/__init__.py
nemo_aligner/models/nlp/gpt/gpt_reward_model.py
nemo_aligner/models/nlp/gpt/gpt_sft_model.py
nemo_aligner/models/nlp/gpt/gpt_steerlm_model.py
nemo_aligner/models/nlp/gpt/megatron_gpt_critic.py
nemo_aligner/models/nlp/gpt/megatron_gpt_dpo_model.py
nemo_aligner/models/nlp/gpt/megatron_gpt_knowledge_distillation.py
nemo_aligner/models/nlp/gpt/megatron_gpt_kto_model.py
nemo_aligner/models/nlp/gpt/megatron_gpt_ppo_actor.py
nemo_aligner/models/nlp/gpt/megatron_gpt_regression_reward_model.py
nemo_aligner/models/nlp/gpt/megatron_gpt_reinforce_actor.py
nemo_aligner/models/nlp/gpt/megatron_gpt_reward_model.py
nemo_aligner/models/nlp/gpt/megatron_gpt_rs_actor.py
nemo_aligner/models/nlp/gpt/megatron_gpt_spin_model.py
nemo_aligner/models/nlp/gpt/reward_critic_clients.py
nemo_aligner/models/nlp/gpt/reward_model_classes.py
nemo_aligner/servers/__init__.py
nemo_aligner/servers/constants.py
nemo_aligner/servers/http_communicator.py
nemo_aligner/utils/__init__.py
nemo_aligner/utils/batch_iterators.py
nemo_aligner/utils/distributed.py
nemo_aligner/utils/parallel_state.py
nemo_aligner-0.7.0.dist-info/LICENSE
nemo_aligner-0.7.0.dist-info/METADATA
nemo_aligner-0.7.0.dist-info/WHEEL
nemo_aligner-0.7.0.dist-info/top_level.txt
nemo_aligner-0.7.0.dist-info/RECORD
