Metadata-Version: 2.2
Name: nemo_aligner
Version: 0.7.0
Summary: NeMo-Aligner - a toolkit for model alignment
Home-page: https://github.com/NVIDIA/NeMo-Aligner
Download-URL: https://github.com/NVIDIA/NeMo-Aligner/releases
Author: NVIDIA
Author-email: nemo-toolkit@nvidia.com
Maintainer: NVIDIA
Maintainer-email: nemo-toolkit@nvidia.com
License: Apache2
Keywords: deep learning,machine learning,gpu,NLP,NeMo,nvidia,pytorch,torch,language,reinforcement learning,RLHF,preference modeling,SteerLM,DPO
Classifier: Development Status :: 3 - Alpha
Classifier: Intended Audience :: Developers
Classifier: Intended Audience :: Science/Research
Classifier: Intended Audience :: Information Technology
Classifier: Topic :: Scientific/Engineering
Classifier: Topic :: Scientific/Engineering :: Mathematics
Classifier: Topic :: Scientific/Engineering :: Image Recognition
Classifier: Topic :: Scientific/Engineering :: Artificial Intelligence
Classifier: Topic :: Software Development :: Libraries
Classifier: Topic :: Software Development :: Libraries :: Python Modules
Classifier: Topic :: Utilities
Classifier: License :: OSI Approved :: Apache Software License
Classifier: Programming Language :: Python :: 3
Classifier: Programming Language :: Python :: 3.9
Classifier: Programming Language :: Python :: 3.10
Classifier: Environment :: Console
Classifier: Natural Language :: English
Classifier: Operating System :: OS Independent
License-File: LICENSE
Requires-Dist: Jinja2~=3.1.4
Requires-Dist: jsonlines
Dynamic: author
Dynamic: author-email
Dynamic: classifier
Dynamic: description
Dynamic: description-content-type
Dynamic: download-url
Dynamic: home-page
Dynamic: keywords
Dynamic: license
Dynamic: maintainer
Dynamic: maintainer-email
Dynamic: requires-dist
Dynamic: summary
